unifi_reconnect-0.1.1.dist-info/METADATA
unifi_reconnect-0.1.1.dist-info/WHEEL
unifi_reconnect-0.1.1.dist-info/entry_points.txt
unifi_reconnect-0.1.1.dist-info/licenses/LICENSE
unifi_reconnect/__init__.py
unifi_reconnect-0.1.1.dist-info/RECORD
