Metadata-Version: 2.1
Name: unifi_reconnect
Version: 0.1.1
Summary: Reconnect a client device on a UniFi network
Author-Email: Jinnatar <jinnak@nocturnal.fi>
License: MIT
Requires-Python: <4.0,>3.9.1
Requires-Dist: absl-py<3.0.0,>=2.1.0
Requires-Dist: unifi-api<2.0.0,>=1.0.3
Requires-Dist: jwt<2.0.0,>=1.3.1
